anole/__init__.py
anole/error.py
anole/fake.py
anole/run.py
anole/setting.py
anole/tool.py
anole-0.2.3.dist-info/LICENSE
anole-0.2.3.dist-info/METADATA
anole-0.2.3.dist-info/WHEEL
anole-0.2.3.dist-info/entry_points.txt
anole-0.2.3.dist-info/top_level.txt
anole-0.2.3.dist-info/RECORD
