Metadata-Version: 2.1
Name: anole
Version: 0.2.3
Summary: Like a anole, fake everything.
Home-page: https://leesoar.com
Author: leesoar
Author-email: secure@tom.com
License: MIT
Keywords: user,agent,user agent,useragent,fake,fake useragent,fake user agent,anole
Platform: UNKNOWN
Classifier: License :: OSI Approved :: MIT License
Classifier: Programming Language :: Python :: 3.5
Classifier: Programming Language :: Python :: 3.6
Classifier: Programming Language :: Python :: 3.7
Classifier: Programming Language :: Python :: Implementation :: CPython
Classifier: Programming Language :: Python :: Implementation :: PyPy
Requires-Python: >=3.3.0
Requires-Dist: faker
Requires-Dist: requests
Requires-Dist: retrying
